{
  "id": "fd46d4e8-8638-4bbe-b0fd-c4efafc54ed3",
  "prevId": "00000000-0000-0000-0000-000000000000",
  "version": "6",
  "dialect": "postgresql",
  "tables": {
    "ins.ins_comments": {
      "name": "ins_comments",
      "schema": "ins",
      "columns": {
        "id": {
          "name": "id",
          "type": "serial",
          "primaryKey": true,
          "notNull": true
        },
        "user_id": {
          "name": "user_id",
          "type": "integer",
          "primaryKey": false,
          "notNull": true
        },
        "post_id": {
          "name": "post_id",
          "type": "integer",
          "primaryKey": false,
          "notNull": true
        },
        "text": {
          "name": "text",
          "type": "text",
          "primaryKey": false,
          "notNull": true
        },
        "created_at": {
          "name": "created_at",
          "type": "timestamp with time zone",
          "primaryKey": false,
          "notNull": true,
          "default": "now()"
        }
      },
      "indexes": {
        "ins_comments_post_user_idx": {
          "name": "ins_comments_post_user_idx",
          "columns": [
            "post_id",
            "user_id"
          ],
          "isUnique": false
        }
      },
      "foreignKeys": {
        "ins_comments_user_id_ins_users_id_fk": {
          "name": "ins_comments_user_id_ins_users_id_fk",
          "tableFrom": "ins_comments",
          "tableTo": "ins_users",
          "schemaTo": "ins",
          "columnsFrom": [
            "user_id"
          ],
          "columnsTo": [
            "id"
          ],
          "onDelete": "cascade",
          "onUpdate": "no action"
        },
        "ins_comments_post_id_ins_posts_id_fk": {
          "name": "ins_comments_post_id_ins_posts_id_fk",
          "tableFrom": "ins_comments",
          "tableTo": "ins_posts",
          "schemaTo": "ins",
          "columnsFrom": [
            "post_id"
          ],
          "columnsTo": [
            "id"
          ],
          "onDelete": "cascade",
          "onUpdate": "no action"
        }
      },
      "compositePrimaryKeys": {},
      "uniqueConstraints": {}
    },
    "ins.ins_follows": {
      "name": "ins_follows",
      "schema": "ins",
      "columns": {
        "follower_id": {
          "name": "follower_id",
          "type": "integer",
          "primaryKey": false,
          "notNull": true
        },
        "following_id": {
          "name": "following_id",
          "type": "integer",
          "primaryKey": false,
          "notNull": true
        },
        "created_at": {
          "name": "created_at",
          "type": "timestamp with time zone",
          "primaryKey": false,
          "notNull": true,
          "default": "now()"
        }
      },
      "indexes": {
        "ins_follows_following_id_idx": {
          "name": "ins_follows_following_id_idx",
          "columns": [
            "following_id"
          ],
          "isUnique": false
        }
      },
      "foreignKeys": {
        "ins_follows_follower_id_ins_users_id_fk": {
          "name": "ins_follows_follower_id_ins_users_id_fk",
          "tableFrom": "ins_follows",
          "tableTo": "ins_users",
          "schemaTo": "ins",
          "columnsFrom": [
            "follower_id"
          ],
          "columnsTo": [
            "id"
          ],
          "onDelete": "cascade",
          "onUpdate": "no action"
        },
        "ins_follows_following_id_ins_users_id_fk": {
          "name": "ins_follows_following_id_ins_users_id_fk",
          "tableFrom": "ins_follows",
          "tableTo": "ins_users",
          "schemaTo": "ins",
          "columnsFrom": [
            "following_id"
          ],
          "columnsTo": [
            "id"
          ],
          "onDelete": "cascade",
          "onUpdate": "no action"
        }
      },
      "compositePrimaryKeys": {
        "ins_follows_follower_id_following_id_pk": {
          "name": "ins_follows_follower_id_following_id_pk",
          "columns": [
            "follower_id",
            "following_id"
          ]
        }
      },
      "uniqueConstraints": {}
    },
    "ins.ins_likes": {
      "name": "ins_likes",
      "schema": "ins",
      "columns": {
        "user_id": {
          "name": "user_id",
          "type": "integer",
          "primaryKey": false,
          "notNull": true
        },
        "post_id": {
          "name": "post_id",
          "type": "integer",
          "primaryKey": false,
          "notNull": true
        },
        "created_at": {
          "name": "created_at",
          "type": "timestamp with time zone",
          "primaryKey": false,
          "notNull": true,
          "default": "now()"
        }
      },
      "indexes": {},
      "foreignKeys": {
        "ins_likes_user_id_ins_users_id_fk": {
          "name": "ins_likes_user_id_ins_users_id_fk",
          "tableFrom": "ins_likes",
          "tableTo": "ins_users",
          "schemaTo": "ins",
          "columnsFrom": [
            "user_id"
          ],
          "columnsTo": [
            "id"
          ],
          "onDelete": "cascade",
          "onUpdate": "no action"
        },
        "ins_likes_post_id_ins_posts_id_fk": {
          "name": "ins_likes_post_id_ins_posts_id_fk",
          "tableFrom": "ins_likes",
          "tableTo": "ins_posts",
          "schemaTo": "ins",
          "columnsFrom": [
            "post_id"
          ],
          "columnsTo": [
            "id"
          ],
          "onDelete": "cascade",
          "onUpdate": "no action"
        }
      },
      "compositePrimaryKeys": {
        "ins_likes_user_id_post_id_pk": {
          "name": "ins_likes_user_id_post_id_pk",
          "columns": [
            "user_id",
            "post_id"
          ]
        }
      },
      "uniqueConstraints": {}
    },
    "ins.ins_posts": {
      "name": "ins_posts",
      "schema": "ins",
      "columns": {
        "id": {
          "name": "id",
          "type": "serial",
          "primaryKey": true,
          "notNull": true
        },
        "user_id": {
          "name": "user_id",
          "type": "integer",
          "primaryKey": false,
          "notNull": true
        },
        "image_url": {
          "name": "image_url",
          "type": "text",
          "primaryKey": false,
          "notNull": true
        },
        "caption": {
          "name": "caption",
          "type": "text",
          "primaryKey": false,
          "notNull": false
        },
        "created_at": {
          "name": "created_at",
          "type": "timestamp with time zone",
          "primaryKey": false,
          "notNull": true,
          "default": "now()"
        },
        "search_vector": {
          "name": "search_vector",
          "type": "tsvector",
          "primaryKey": false,
          "notNull": false
        }
      },
      "indexes": {
        "ins_posts_user_id_idx": {
          "name": "ins_posts_user_id_idx",
          "columns": [
            "user_id"
          ],
          "isUnique": false
        },
        "ins_posts_search_vector_idx": {
          "name": "ins_posts_search_vector_idx",
          "columns": [
            "search_vector"
          ],
          "isUnique": false
        }
      },
      "foreignKeys": {
        "ins_posts_user_id_ins_users_id_fk": {
          "name": "ins_posts_user_id_ins_users_id_fk",
          "tableFrom": "ins_posts",
          "tableTo": "ins_users",
          "schemaTo": "ins",
          "columnsFrom": [
            "user_id"
          ],
          "columnsTo": [
            "id"
          ],
          "onDelete": "cascade",
          "onUpdate": "no action"
        }
      },
      "compositePrimaryKeys": {},
      "uniqueConstraints": {}
    },
    "ins.ins_users": {
      "name": "ins_users",
      "schema": "ins",
      "columns": {
        "id": {
          "name": "id",
          "type": "serial",
          "primaryKey": true,
          "notNull": true
        },
        "username": {
          "name": "username",
          "type": "varchar(50)",
          "primaryKey": false,
          "notNull": true
        },
        "email": {
          "name": "email",
          "type": "varchar(255)",
          "primaryKey": false,
          "notNull": true
        },
        "password_hash": {
          "name": "password_hash",
          "type": "text",
          "primaryKey": false,
          "notNull": true
        },
        "bio": {
          "name": "bio",
          "type": "text",
          "primaryKey": false,
          "notNull": false
        },
        "avatar_url": {
          "name": "avatar_url",
          "type": "text",
          "primaryKey": false,
          "notNull": false
        },
        "created_at": {
          "name": "created_at",
          "type": "timestamp with time zone",
          "primaryKey": false,
          "notNull": true,
          "default": "now()"
        }
      },
      "indexes": {},
      "foreignKeys": {},
      "compositePrimaryKeys": {},
      "uniqueConstraints": {
        "ins_users_username_unique": {
          "name": "ins_users_username_unique",
          "nullsNotDistinct": false,
          "columns": [
            "username"
          ]
        },
        "ins_users_email_unique": {
          "name": "ins_users_email_unique",
          "nullsNotDistinct": false,
          "columns": [
            "email"
          ]
        }
      }
    }
  },
  "enums": {},
  "schemas": {
    "ins": "ins"
  },
  "_meta": {
    "columns": {},
    "schemas": {},
    "tables": {}
  }
}